best/__init__.py
best/integration/__init__.py
best/unit/__init__.py
best/unit/conftest.py
best/unit/test_glue_session.py
best/unit/test_glue_session_demo.py
best/unit/test_session_apis.py
gaussian_analytic-19.4.6.dist-info/LICENSE.txt
gaussian_analytic-19.4.6.dist-info/METADATA
gaussian_analytic-19.4.6.dist-info/WHEEL
gaussian_analytic-19.4.6.dist-info/top_level.txt
gaussian_analytic-19.4.6.dist-info/RECORD
